drift_mqtt/VERSION
drift_mqtt/__init__.py
drift_mqtt/client.py
drift_mqtt-0.2.2.dist-info/LICENSE
drift_mqtt-0.2.2.dist-info/METADATA
drift_mqtt-0.2.2.dist-info/WHEEL
drift_mqtt-0.2.2.dist-info/top_level.txt
drift_mqtt-0.2.2.dist-info/RECORD
