Metadata-Version: 2.1
Name: drift-mqtt
Version: 0.2.2
Summary: A wrapper around Python Paho Mqtt library
Home-page: https://gitlab.panda.technology/drift/sdk/drift-mqtt
Author: PANDA, GmbH
Author-email: info@panda.technology
Requires-Python: >=3.7
License-File: LICENSE
Requires-Dist: paho-mqtt ~=1.6.0
Provides-Extra: format
Requires-Dist: black ~=22.8.0 ; extra == 'format'
Provides-Extra: lint
Requires-Dist: pylint ~=2.15.3 ; extra == 'lint'
Provides-Extra: test
Requires-Dist: pytest ~=7.1.3 ; extra == 'test'
Requires-Dist: pytest-mock ~=3.8.2 ; extra == 'test'
